frne.cpython-35m-darwin.so
ropy/__init__.py
ropy/backend/Connector.py
ropy/backend/__init__.py
ropy/backend/api.py
ropy/backend/PyPlot/EllipsePlot.py
ropy/backend/PyPlot/PyPlot.py
ropy/backend/PyPlot/PyPlot2.py
ropy/backend/PyPlot/RobotPlot.py
ropy/backend/PyPlot/RobotPlot2.py
ropy/backend/PyPlot/__init__.py
ropy/backend/PyPlot/functions.py
ropy/backend/Sim/Sim.py
ropy/backend/Sim/__init__.py
ropy/backend/urdf/__init__.py
ropy/backend/urdf/urdf.py
ropy/backend/urdf/utils.py
ropy/backend/xacro/__init__.py
ropy/backend/xacro/cli.py
ropy/backend/xacro/color.py
ropy/backend/xacro/xmlutils.py
ropy/models/Frankie.py
ropy/models/Panda.py
ropy/models/PandaMDH.py
ropy/models/PandaURDF.py
ropy/models/Puma560.py
ropy/models/UR5.py
ropy/models/__init__.py
ropy/models/mdl_lbr7.py
ropy/models/mdl_mico.py
ropy/models/mdl_panda.py
ropy/models/mdl_sawyer.py
ropy/models/wx250s.py
ropy/models/xacro/interbotix/meshes/interbotix_black.png
ropy/models/xacro/interbotix/meshes/meshes_px100/PXA-100-M-1-Base.stl
ropy/models/xacro/interbotix/meshes/meshes_px100/PXA-100-M-2-Shoulder.stl
ropy/models/xacro/interbotix/meshes/meshes_px100/PXA-100-M-3-UA.stl
ropy/models/xacro/interbotix/meshes/meshes_px100/PXA-100-M-4-Forearm.stl
ropy/models/xacro/interbotix/meshes/meshes_px100/PXA-100-M-5-Wrist-Gripper.stl
ropy/models/xacro/interbotix/meshes/meshes_px100/PXA-100-M-6-Gripper-Prop.stl
ropy/models/xacro/interbotix/meshes/meshes_px100/PXA-100-M-7-Gripper-Bar.stl
ropy/models/xacro/interbotix/meshes/meshes_px100/PXA-100-M-8-Finger.stl
ropy/models/xacro/interbotix/meshes/meshes_px150/PXA-150-M-1-Base.stl
ropy/models/xacro/interbotix/meshes/meshes_px150/PXA-150-M-2-Shoulder.stl
ropy/models/xacro/interbotix/meshes/meshes_px150/PXA-150-M-3-UA.stl
ropy/models/xacro/interbotix/meshes/meshes_px150/PXA-150-M-4-Forearm.stl
ropy/models/xacro/interbotix/meshes/meshes_px150/PXA-150-M-5-Wrist.stl
ropy/models/xacro/interbotix/meshes/meshes_px150/PXA-150-M-6-Gripper.stl
ropy-0.3.7.dist-info/LICENSE
ropy-0.3.7.dist-info/METADATA
ropy-0.3.7.dist-info/WHEEL
ropy-0.3.7.dist-info/top_level.txt
ropy-0.3.7.dist-info/RECORD
