Metadata-Version: 2.1
Name: ropy
Version: 0.3.7
Summary: A Python library for robot control
Home-page: https://github.com/jhavl/ropy
Author: Jesse Haviland
License: MIT
Keywords: robotics vision arm kinematics ros
Platform: UNKNOWN
Requires-Python: >=3.5
Requires-Dist: numpy
Requires-Dist: spatialmath-python (>=0.7.1)
Requires-Dist: scipy
Requires-Dist: matplotlib
